own_comments/__init__.py
own_comments/crud.py
own_comments/database.py
own_comments/helpers.py
own_comments/main.py
own_comments/models.py
own_comments/notification.py
own_comments/schemas.py
own_comments/settings.py
own_comments-0.1.0a4.dist-info/LICENSE
own_comments-0.1.0a4.dist-info/WHEEL
own_comments-0.1.0a4.dist-info/METADATA
own_comments-0.1.0a4.dist-info/RECORD
